ipds/__init__.py
ipds/cli.py
ipds/core/__init__.py
ipds/core/asn.py
ipds/core/geolocation.py
ipds/core/ip_info.py
ipds/core/whois.py
ipds/utils/__init__.py
ipds/utils/conversion.py
ipds/utils/network.py
ipds/utils/validation.py
ipds-1.0.1.dist-info/licenses/LICENSE
tests/__init__.py
tests/test_conversion.py
tests/test_ip_info.py
tests/test_validation.py
ipds-1.0.1.dist-info/METADATA
ipds-1.0.1.dist-info/WHEEL
ipds-1.0.1.dist-info/entry_points.txt
ipds-1.0.1.dist-info/top_level.txt
ipds-1.0.1.dist-info/RECORD
