Metadata-Version: 2.4
Name: ipds
Version: 1.0.1
Summary: IP Describe Library - Comprehensive IP information lookup tool
Home-page: https://github.com/sigmd-com/ipds-py
Author: Juan Lee
Author-email: Juan Lee <juan.lee@sigmd.com>
License: MIT
Requires-Python: >=3.12
License-File: LICENSE
Requires-Dist: requests>=2.25.0
Provides-Extra: dev
Requires-Dist: pytest>=6.0; extra == "dev"
Requires-Dist: pytest-cov>=2.0; extra == "dev"
Requires-Dist: black>=21.0; extra == "dev"
Requires-Dist: flake8>=3.8; extra == "dev"
Requires-Dist: mypy>=0.800; extra == "dev"
Dynamic: author
Dynamic: home-page
Dynamic: license-file
Dynamic: requires-python
